moneytoring/__init__.py
moneytoring/commandline.py
moneytoring/csv.py
moneytoring/parser.py
moneytoring/query.py
moneytoring-1.3.2.dist-info/METADATA
moneytoring-1.3.2.dist-info/WHEEL
moneytoring-1.3.2.dist-info/entry_points.txt
moneytoring-1.3.2.dist-info/top_level.txt
moneytoring-1.3.2.dist-info/RECORD
