Metadata-Version: 2.1
Name: moneytoring
Version: 1.3.2
Summary: A python budgeting tool
Home-page: https://github.com/arthuRHD/moneytoring
Author: Arthur RICHARD
Author-email: arthur.richard@protonmail.com
License: UNKNOWN
Platform: UNKNOWN
Classifier: Programming Language :: Python :: 3
Classifier: License :: OSI Approved :: MIT License
Classifier: Operating System :: OS Independent
Requires-Python: >=3.6
